dihub_cqrs/__init__.py
dihub_cqrs/__internal/dispatchers/__init__.py
dihub_cqrs/__internal/dispatchers/dispatcher.py
dihub_cqrs/__internal/dispatchers/static_dispatcher.py
dihub_cqrs/__internal/helpers.py
dihub_cqrs/__internal/query_busses/__init__.py
dihub_cqrs/__internal/query_busses/query_bus.py
dihub_cqrs/__internal/query_busses/static_query_bus.py
dihub_cqrs/constants.py
dihub_cqrs/decorators.py
dihub_cqrs/dihub_cqrs_module.py
dihub_cqrs/exceptions.py
dihub_cqrs/types.py
dihub_cqrs-0.1.4.dist-info/LICENSE
dihub_cqrs-0.1.4.dist-info/METADATA
dihub_cqrs-0.1.4.dist-info/WHEEL
dihub_cqrs-0.1.4.dist-info/RECORD
