Metadata-Version: 2.1
Name: dihub-cqrs
Version: 0.1.4
Summary: A CQRS module for DIHub
Home-page: https://github.com/alfarih31/dihub-cqrs
License: BSD
Author: Alfarih Faza
Author-email: alfarihfz@gmail.com
Requires-Python: >=3.10,<4.0
Classifier: License :: Other/Proprietary License
Classifier: Programming Language :: Python :: 3
Classifier: Programming Language :: Python :: 3.10
Classifier: Programming Language :: Python :: 3.11
Requires-Dist: dihub (>=0.1.1,<0.2.0)
Project-URL: Repository, https://github.com/alfarih31/dihub-cqrs
